LICENSE
MANIFEST.in
README.md
setup.cfg
setup.py
django_pf_billing.egg-info/PKG-INFO
django_pf_billing.egg-info/SOURCES.txt
django_pf_billing.egg-info/dependency_links.txt
django_pf_billing.egg-info/requires.txt
django_pf_billing.egg-info/top_level.txt
docs/intro.txt
pf_billing/__init__.py
pf_billing/admin.py
pf_billing/apps.py
pf_billing/errors.py
pf_billing/forms.py
pf_billing/interface.py
pf_billing/models.py
pf_billing/tests.py
pf_billing/utils.py
pf_billing/migrations/0001_initial.py
pf_billing/migrations/__init__.py